setup.cfg
setup.py
tco/__init__.py
tco.egg-info/PKG-INFO
tco.egg-info/SOURCES.txt
tco.egg-info/dependency_links.txt
tco.egg-info/top_level.txt