Metadata-Version: 1.0
Name: tco
Version: 1.2.1
Summary: Tail Call Optimization for Python
Home-page: https://github.com/baruchel/tco
Author: Thomas Baruchel
Author-email: baruchel@gmx.com
License: MIT
Platform: UNKNOWN
